litecli/AUTHORS
litecli/__init__.py
litecli/clibuffer.py
litecli/clistyle.py
litecli/clitoolbar.py
litecli/completion_refresher.py
litecli/config.py
litecli/key_bindings.py
litecli/lexer.py
litecli/liteclirc
litecli/main.py
litecli/sqlcompleter.py
litecli/sqlexecute.py
litecli/packages/__init__.py
litecli/packages/completion_engine.py
litecli/packages/filepaths.py
litecli/packages/parseutils.py
litecli/packages/prompt_utils.py
litecli/packages/special/__init__.py
litecli/packages/special/dbcommands.py
litecli/packages/special/favoritequeries.py
litecli/packages/special/iocommands.py
litecli/packages/special/llm.py
litecli/packages/special/main.py
litecli/packages/special/utils.py
litecli-1.15.0.dist-info/LICENSE
litecli-1.15.0.dist-info/METADATA
litecli-1.15.0.dist-info/WHEEL
litecli-1.15.0.dist-info/entry_points.txt
litecli-1.15.0.dist-info/top_level.txt
litecli-1.15.0.dist-info/RECORD
