Metadata-Version: 2.2
Name: litecli
Version: 1.15.0
Summary: CLI for SQLite Databases with auto-completion and syntax highlighting.
Author-email: dbcli <litecli-users@googlegroups.com>
License: BSD
Project-URL: homepage, https://github.com/dbcli/litecli
Requires-Python: >=3.9
License-File: LICENSE
Requires-Dist: cli-helpers[styles]>=2.2.1
Requires-Dist: click>=4.1
Requires-Dist: configobj>=5.0.5
Requires-Dist: prompt-toolkit<4.0.0,>=3.0.3
Requires-Dist: pygments>=1.6
Requires-Dist: sqlparse>=0.4.4
Requires-Dist: setuptools
Requires-Dist: pip
Provides-Extra: ai
Requires-Dist: llm; extra == "ai"
Provides-Extra: dev
Requires-Dist: behave>=1.2.6; extra == "dev"
Requires-Dist: coverage>=7.2.7; extra == "dev"
Requires-Dist: pexpect>=4.9.0; extra == "dev"
Requires-Dist: pytest>=7.4.4; extra == "dev"
Requires-Dist: pytest-cov>=4.1.0; extra == "dev"
Requires-Dist: tox>=4.8.0; extra == "dev"
Requires-Dist: pdbpp>=0.10.3; extra == "dev"
Requires-Dist: llm>=0.19.0; extra == "dev"
